jcdiq/__init__.py
jcdiq/hello_world.py
jiacheng_dgp_dpf-0.1.dist-info/LICENSE
jiacheng_dgp_dpf-0.1.dist-info/METADATA
jiacheng_dgp_dpf-0.1.dist-info/WHEEL
jiacheng_dgp_dpf-0.1.dist-info/top_level.txt
jiacheng_dgp_dpf-0.1.dist-info/RECORD
